Products.SimpleCalendar-configure.zcml
README.txt
setup.py
Products/__init__.py
Products.SimpleCalendar.egg-info/PKG-INFO
Products.SimpleCalendar.egg-info/SOURCES.txt
Products.SimpleCalendar.egg-info/dependency_links.txt
Products.SimpleCalendar.egg-info/entry_points.txt
Products.SimpleCalendar.egg-info/namespace_packages.txt
Products.SimpleCalendar.egg-info/not-zip-safe
Products.SimpleCalendar.egg-info/requires.txt
Products.SimpleCalendar.egg-info/top_level.txt
Products/SimpleCalendar/__init__.py
Products/SimpleCalendar/changes.txt
Products/SimpleCalendar/config.py
Products/SimpleCalendar/configure.zcml
Products/SimpleCalendar/hacks.py
Products/SimpleCalendar/interfaces.py
Products/SimpleCalendar/profiles.zcml
Products/SimpleCalendar/readme.txt
Products/SimpleCalendar/setuphandlers.py
Products/SimpleCalendar/tests.py
Products/SimpleCalendar/version.txt
Products/SimpleCalendar/zope2.py
Products/SimpleCalendar/content/SimpleCalendar.py
Products/SimpleCalendar/content/__init__.py
Products/SimpleCalendar/content/adapters.py
Products/SimpleCalendar/profiles/default/SimpleCalendar_marker.txt
Products/SimpleCalendar/profiles/default/cssregistry.xml
Products/SimpleCalendar/profiles/default/factorytool.xml
Products/SimpleCalendar/profiles/default/import_steps.xml
Products/SimpleCalendar/profiles/default/jsregistry.xml
Products/SimpleCalendar/profiles/default/metadata.xml
Products/SimpleCalendar/profiles/default/skins.xml
Products/SimpleCalendar/profiles/default/types.xml
Products/SimpleCalendar/profiles/default/types/SimpleCalendar.xml
docs/HISTORY.txt