Metadata-Version: 1.0
Name: Products.SimpleCalendar
Version: 1.0a3
Summary: Simple to install and use calendaring solution
Home-page: http://www.nidelven-it.no/d
Author: Morten W. Petersen
Author-email: info@nidelven-it.no
License: GPL
Keywords: python zope plone calendaring calendar events
Platform: UNKNOWN
Classifier: Programming Language :: Python
Classifier: Development Status :: 3 - Alpha
Classifier: Environment :: Web Environment
Classifier: Framework :: Plone :: 4.1
Classifier: Operating System :: OS Independent
Classifier: Topic :: Office/Business :: Groupware
Classifier: Topic :: Office/Business :: Scheduling
